capf/__init__.py
capf/adaptors.py
capf/core.py
capf/exceptions.py
capf/parser.py
capf/py.typed
capf/reader.py
capf/validators.py
capf-0.1.0.dist-info/METADATA
capf-0.1.0.dist-info/WHEEL
capf-0.1.0.dist-info/licenses/LICENSE
capf-0.1.0.dist-info/RECORD
